{
    "assignments": [
        {
            "title": "In class quizzes (3)",
            "due_date": "2025-01-30",
            "due_time": "N/A",
            "weight": 8,
            "difficulty": 0
        },
        {
            "title": "In class quizzes (3)",
            "due_date": "2025-03-13",
            "due_time": "N/A",
            "weight": 8,
            "difficulty": 0
        },
        {
            "title": "In class quizzes (3)",
            "due_date": "2025-04-03",
            "due_time": "N/A",
            "weight": 8,
            "difficulty": 0
        },
        {
            "title": "Midterm examination",
            "due_date": "2025-03-01",
            "due_time": "N/A",
            "weight": 26,
            "difficulty": 0
        },
        {
            "title": "Five-minute, policy elevator pitch audiovisual presentation",
            "due_date": "2025-03-31",
            "due_time": "08:00",
            "weight": 15,
            "difficulty": 0
        }
    ],
    "tests": [
        {
            "title": "Final Exam",
            "date": "2025-04-07",
            "time": "N/A",
            "weight": 35
        }
    ],
    "schedule": [
        {
            "days": [
                "Thursday"
            ],
            "time": "14:30–16:30",
            "location": "N/A"
        }
    ]
}